Metadata-Version: 1.0
Name: dgb-distributions
Version: 0.1
Summary: Gaussian distributions
Home-page: UNKNOWN
Author: Alexander Bennett
Author-email: zanderwhiteleybennett@gmail.com
License: UNKNOWN
Platform: UNKNOWN
